catnekaise_actions_constructs/__init__.py
catnekaise_actions_constructs/py.typed
catnekaise_actions_constructs/_jsii/__init__.py
catnekaise_actions_constructs/_jsii/actions-constructs@0.2.30.jsii.tgz
catnekaise.actions_constructs-0.2.30.dist-info/LICENSE
catnekaise.actions_constructs-0.2.30.dist-info/METADATA
catnekaise.actions_constructs-0.2.30.dist-info/WHEEL
catnekaise.actions_constructs-0.2.30.dist-info/top_level.txt
catnekaise.actions_constructs-0.2.30.dist-info/RECORD
