Metadata-Version: 2.1
Name: catnekaise.actions-constructs
Version: 0.2.30
Summary: CDK Constructs for integrating GitHub Actions and AWS.
Home-page: https://github.com/catnekaise/actions-constructs.git
Author: Daniel Jonsén<djonser1@gmail.com>
License: Apache-2.0
Project-URL: Source, https://github.com/catnekaise/actions-constructs.git
Classifier: Intended Audience :: Developers
Classifier: Operating System :: OS Independent
Classifier: Programming Language :: JavaScript
Classifier: Programming Language :: Python :: 3 :: Only
Classifier: Programming Language :: Python :: 3.8
Classifier: Programming Language :: Python :: 3.9
Classifier: Programming Language :: Python :: 3.10
Classifier: Programming Language :: Python :: 3.11
Classifier: Typing :: Typed
Classifier: Development Status :: 5 - Production/Stable
Classifier: License :: OSI Approved
Requires-Python: ~=3.8
License-File: LICENSE
Requires-Dist: aws-cdk-lib<3.0.0,>=2.82.0
Requires-Dist: catnekaise.cdk-iam-utilities<0.0.31,>=0.0.30
Requires-Dist: constructs<11.0.0,>=10.0.5
Requires-Dist: jsii<2.0.0,>=1.103.1
Requires-Dist: publication>=0.0.3
Requires-Dist: typeguard<5.0.0,>=2.13.3
